lavos.py
lavos-0.1.0.dist-info/METADATA
lavos-0.1.0.dist-info/WHEEL
lavos-0.1.0.dist-info/RECORD
