Metadata-Version: 2.1
Name: lavos
Version: 0.1.0
Summary: Lavos: A Pythonic Cron Expression Serializer with Fluent Syntax.
Author: Rafael Izidoro
Author-email: izidoro.me@gmail.com
Requires-Python: >=3.11,<4.0
Classifier: Programming Language :: Python :: 3
Classifier: Programming Language :: Python :: 3.11
